pippy/IR.py
pippy/LoadModule.py
pippy/ModelSplit.py
pippy/PipelineSchedule.py
pippy/PipelineStage.py
pippy/SaveModule.py
pippy/__init__.py
pippy/backward.py
pippy/debug.py
pippy/events.py
pippy/microbatch.py
pippy/utils.py
pippy/version.py
pippy/visualizer.py
test/__init__.py
test/hf_test.py
test/local_test_autosplit.py
test/local_test_c10d_ddp.py
test/local_test_checkpoint.py
test/local_test_chunkspec.py
test/local_test_null_coalesce_accumulate.py
test/local_test_optim.py
test/min_gpt_pp_tp.py
test/min_gpt_tracing.py
test/test_bwd.py
test/test_cpu_init.py
test/test_fwd.py
test/test_ir.py
test/test_pipe.py
test/test_pipe_bwd.py
test/test_pipeline_schedule.py
torchpippy-0.2.0.dist-info/LICENSE
torchpippy-0.2.0.dist-info/METADATA
torchpippy-0.2.0.dist-info/WHEEL
torchpippy-0.2.0.dist-info/top_level.txt
torchpippy-0.2.0.dist-info/RECORD
