Metadata-Version: 2.1
Name: torchpippy
Version: 0.2.0
Summary: Pipeline Parallelism for PyTorch
Home-page: https://github.com/pytorch/PiPPy
Author: PiPPy Team
License: BSD
License-File: LICENSE
Requires-Dist: torch >=2.2.0.dev
